enhanced_webdriver/EnhancedWebdriver.py
enhanced_webdriver/__init__.py
EnhancedWebdriver-0.1.8.dist-info/LICENSE
EnhancedWebdriver-0.1.8.dist-info/METADATA
EnhancedWebdriver-0.1.8.dist-info/WHEEL
EnhancedWebdriver-0.1.8.dist-info/top_level.txt
EnhancedWebdriver-0.1.8.dist-info/RECORD
